odoo/addons/l10n_jp_partner_title_qweb/README.rst
odoo/addons/l10n_jp_partner_title_qweb/__init__.py
odoo/addons/l10n_jp_partner_title_qweb/__manifest__.py
odoo/addons/l10n_jp_partner_title_qweb/i18n/ja.po
odoo/addons/l10n_jp_partner_title_qweb/i18n/ja_JP.po
odoo/addons/l10n_jp_partner_title_qweb/i18n/l10n_jp_partner_title_qweb.pot
odoo/addons/l10n_jp_partner_title_qweb/migrations/19.0.1.0.0/post-migration.py
odoo/addons/l10n_jp_partner_title_qweb/models/__init__.py
odoo/addons/l10n_jp_partner_title_qweb/models/res_partner.py
odoo/addons/l10n_jp_partner_title_qweb/readme/CONFIGURE.md
odoo/addons/l10n_jp_partner_title_qweb/readme/CONTRIBUTORS.md
odoo/addons/l10n_jp_partner_title_qweb/readme/DESCRIPTION.md
odoo/addons/l10n_jp_partner_title_qweb/readme/ROADMAP.md
odoo/addons/l10n_jp_partner_title_qweb/report/templates.xml
odoo/addons/l10n_jp_partner_title_qweb/static/description/icon.png
odoo/addons/l10n_jp_partner_title_qweb/static/description/index.html
odoo/addons/l10n_jp_partner_title_qweb/static/description/pdf-image.png
odoo/addons/l10n_jp_partner_title_qweb/views/res_partner_views.xml
odoo_addon_l10n_jp_partner_title_qweb-19.0.1.0.0.3.dist-info/METADATA
odoo_addon_l10n_jp_partner_title_qweb-19.0.1.0.0.3.dist-info/WHEEL
odoo_addon_l10n_jp_partner_title_qweb-19.0.1.0.0.3.dist-info/top_level.txt
odoo_addon_l10n_jp_partner_title_qweb-19.0.1.0.0.3.dist-info/RECORD
