Metadata-Version: 2.1
Name: odoo-addon-l10n_jp_partner_title_qweb
Version: 19.0.1.0.0.3
Requires-Dist: odoo==19.0.*
Summary: Japan Partner Title QWeb
Home-page: https://github.com/OCA/l10n-japan
License: LGPL-3
Author: Quartile, Odoo Community Association (OCA)
Author-email: support@odoo-community.org
Classifier: Programming Language :: Python
Classifier: Framework :: Odoo
Classifier: Framework :: Odoo :: 19.0
Classifier: License :: OSI Approved :: GNU Lesser General Public License v3 (LGPLv3)
